funstall/__init__.py
funstall/application_context.py
funstall/cli.py
funstall/config.py
funstall/custom_click_types.py
funstall/proc_utils.py
funstall/system_paths.py
funstall/installation/__init__.py
funstall/installation/installation.py
funstall/installation/model.py
funstall/installation/npm.py
funstall/installation/nushell.py
funstall/installation/pacman.py
funstall/installation/pip.py
funstall/installation/source_priorities.py
funstall/packages/__init__.py
funstall/packages/installs.py
funstall/packages/installs_test.py
funstall/packages/model.py
funstall/packages/package_definitions.py
funstall/packages/validate_package_file.py
funstall-0.1.6.dist-info/METADATA
funstall-0.1.6.dist-info/WHEEL
funstall-0.1.6.dist-info/entry_points.txt
funstall-0.1.6.dist-info/licenses/LICENSE
funstall-0.1.6.dist-info/RECORD
