Metadata-Version: 2.4
Name: funstall
Version: 0.1.6
Summary: The fun cross-platform package manager!
Project-URL: Homepage, https://github.com/hbibel/funstall
Project-URL: Repository, https://github.com/hbibel/funstall.git
Project-URL: Issues, https://github.com/hbibel/funstall/issues
Author: Hannes Bibel
License-Expression: AGPL-3.0-or-later
License-File: LICENSE
Classifier: Development Status :: 3 - Alpha
Classifier: Intended Audience :: Developers
Classifier: Intended Audience :: System Administrators
Classifier: License :: OSI Approved :: GNU Affero General Public License v3 or later (AGPLv3+)
Classifier: Operating System :: OS Independent
Classifier: Programming Language :: Python :: 3.13
Classifier: Topic :: System :: Installation/Setup
Classifier: Topic :: System :: Software Distribution
Classifier: Topic :: System :: Systems Administration
Classifier: Topic :: Utilities
Requires-Python: >=3.13
Requires-Dist: click>=8.3.0
Requires-Dist: httpx>=0.28.1
Requires-Dist: packaging>=25.0
Requires-Dist: pydantic-settings>=2.11.0
Requires-Dist: pydantic>=2.11.9
Requires-Dist: pytest-mock>=3.15.1
Requires-Dist: pyyaml>=6.0.3
Requires-Dist: tomli-w>=1.2.0
